Metadata-Version: 2.1
Name: soda-core-denodo
Version: 3.5.6
License-File: LICENSE
Requires-Dist: soda-core==3.5.6
Requires-Dist: soda-core-postgres==3.5.6
